roul/__init__.py
roul/asn/__init__.py
roul/asn/bgptools.py
roul/ip/__init__.py
roul/ip/radix.py
roul/passwd/__init__.py
roul/thread/__init__.py
roul-0.1.3.dist-info/licenses/LICENSE
roul-0.1.3.dist-info/METADATA
roul-0.1.3.dist-info/WHEEL
roul-0.1.3.dist-info/top_level.txt
roul-0.1.3.dist-info/RECORD
